apiprime/__init__.py
apiprime/__main__.py
apiprime-0.1.0.dist-info/LICENSE
apiprime-0.1.0.dist-info/METADATA
apiprime-0.1.0.dist-info/WHEEL
apiprime-0.1.0.dist-info/entry_points.txt
apiprime-0.1.0.dist-info/top_level.txt
apiprime-0.1.0.dist-info/RECORD
